soraya/__init__.py
soraya/soraya.py
soraya-0.0.9.dist-info/LICENSE
soraya-0.0.9.dist-info/METADATA
soraya-0.0.9.dist-info/WHEEL
soraya-0.0.9.dist-info/top_level.txt
soraya-0.0.9.dist-info/RECORD
