Metadata-Version: 2.1
Name: soraya
Version: 0.0.9
Summary: Soraya is a package that selects the most important features using an innovative hybrid method for both regression and classification problems.
Home-page: https://github.com/Gashmard/Soraya
Author: Hassan Gashmard
Author-email: HassanGashmard@gmail.com
License: MIT
Classifier: Programming Language :: Python :: 3
Classifier: License :: OSI Approved :: MIT License
Classifier: Operating System :: OS Independent
Requires-Python: >=3.6
License-File: LICENSE
